{
  "formatVersion": "1",
  "header": {
    "description": "Maintain System Information",
    "originalLanguage": "en"
  },
  "serviceConfiguration": {
    "serviceBinding": "/ESRCC/UI_SYSINFO_O4",
    "serviceName": "/ESRCC/UI_SYSINFO_O4",
    "serviceVersion": "0001",
    "rootEntitySet": "SystemInfoAll",
    "name": "Maintain System Information",
    "configurationGroup": "/ESRCC/BC_GROUP1",
    "skipRootEntity": true
  },
  "appConfiguration": {
    "listReport": {},
    "objectPages": [
      {
        "entitySet": "SystemInfo"
      },
      {
        "entitySet": "SystemInfoText"
      }
    ],
    "tableSettings": [
      {
        "entitySet": "SystemInfo",
        "tableType": "gridTable",
        "creationModeName": "creationRow",
        "enableFullScreen": true,
        "rowCountMode": "auto"
      },
      {
        "entitySet": "SystemInfoAll"
      },
      {
        "entitySet": "SystemInfoText",
        "tableType": "gridTable",
        "creationModeName": "creationRow",
        "enableFullScreen": true
      }
    ]
  }
}